byted_rtc_robot_api_v2/__init__.py
byted_rtc_robot_api_v2-0.0.44.15.dist-info/METADATA
byted_rtc_robot_api_v2-0.0.44.15.dist-info/WHEEL
byted_rtc_robot_api_v2-0.0.44.15.dist-info/top_level.txt
byted_rtc_robot_api_v2-0.0.44.15.dist-info/RECORD
