Metadata-Version: 2.1
Name: byted-rtc-robot-api-v2
Version: 0.0.44.15
Summary: Collect byted metrics to evaluate
Author: serverinspector
Author-email: serverinspector@wearehackerone.com
Requires-Dist: requests
